sympt/__init__.py
sympt/classes.py
sympt/logging_config.py
sympt/solver.py
sympt/utils.py
sympt-1.2.1.dist-info/LICENSE
sympt-1.2.1.dist-info/METADATA
sympt-1.2.1.dist-info/WHEEL
sympt-1.2.1.dist-info/top_level.txt
sympt-1.2.1.dist-info/RECORD
