Metadata-Version: 2.2
Name: sympt
Version: 1.2.1
Summary: A solver for perturbative expansions in quantum systems
Author-email: Monica Benito <monica.benito@uni-a.de>, Giovanni Francesco Diotallevi <francesco.diotallevi@uni-a.de>, Irving Leander Reascos Valencia <irving.reascos.valencia@uni-a.de>
License: MIT License
Project-URL: Repository, https://github.com/qcode-uni-a/sympt
Classifier: Development Status :: 3 - Alpha
Classifier: License :: OSI Approved :: MIT License
Classifier: Operating System :: OS Independent
Classifier: Intended Audience :: Science/Research
Classifier: Programming Language :: Python
Classifier: Programming Language :: Python :: 3
Classifier: Programming Language :: Python :: 3.8
Classifier: Programming Language :: Python :: 3.9
Classifier: Programming Language :: Python :: 3.10
Classifier: Programming Language :: Python :: 3.11
Classifier: Programming Language :: Python :: 3.12
Classifier: Topic :: Scientific/Engineering
Requires-Python: >=3.8
License-File: LICENSE
Requires-Dist: ipython==8.20
Requires-Dist: multimethod==1.12
Requires-Dist: numpy==2.0
Requires-Dist: sympy==1.13.3
Requires-Dist: tabulate==0.9
Requires-Dist: tqdm==4.66
Requires-Dist: colorama
